README.rst
setup.cfg
setup.py
iterext/__init__.py
iterext/extras.py
iterext/recipes.py
iterext.egg-info/PKG-INFO
iterext.egg-info/SOURCES.txt
iterext.egg-info/dependency_links.txt
iterext.egg-info/top_level.txt