Metadata-Version: 1.1
Name: iterext
Version: 1.0
Summary: iterext: Python itertools recipes.
Home-page: http://github.com/aguil/iterext
Author: Jason Aguilon
Author-email: jaguilon@gmail.com
License: UNKNOWN
Platform: UNKNOWN
Classifier: Development Status :: 5 - Production/Stable
Classifier: Intended Audience :: Developers
Classifier: Topic :: Software Development :: Libraries
Classifier: Topic :: Utilities
Classifier: Programming Language :: Python :: 2
Classifier: Programming Language :: Python :: 2.7
